modbusclc/__init__.py
modbusclc/__main__.py
modbusclc/cli.py
modbusclc-0.3.0.dist-info/LICENSE
modbusclc-0.3.0.dist-info/METADATA
modbusclc-0.3.0.dist-info/WHEEL
modbusclc-0.3.0.dist-info/top_level.txt
modbusclc-0.3.0.dist-info/RECORD
