Metadata-Version: 2.1
Name: modbusclc
Version: 0.3.0
Summary: Modbus Command Line Client
Home-page: https://github.com/RavenKyu/modbus-command-line-client
Author: Duk Kyu Lim
Author-email: hong18s@gmail.com
License: MIT
Keywords: cli,modbus
Platform: UNKNOWN
Classifier: Development Status :: 4 - Beta
Classifier: Environment :: Console
Classifier: Operating System :: MacOS
Classifier: Operating System :: Microsoft :: Windows
Classifier: Operating System :: POSIX :: Linux
Classifier: Programming Language :: Python :: 3.7
Classifier: Programming Language :: Python :: 3.8
Classifier: Topic :: Utilities
Classifier: License :: OSI Approved :: MIT License
Requires-Dist: cliparse
Requires-Dist: pymodbus
Requires-Dist: PyYaml
